{
    "Path 1": [
        {
            "treeNode": {
                "nodeId": "2",
                "uid": "f4c60645-1141-4cf1-b181-ef21cc0e871d"
            },
            "predicate": "(Slt (ReadLSB w32 0 b_sym) (ReadLSB w32 0 a_sym))",
            "nodeTrueQuery": [],
            "nodeFalseQuery": [],
            "variables": [
                "b_sym",
                "a_sym"
            ],
            "IMap": {
                "b_sym": "ac331db2-7951-4261-8a5c-6056e6b68ca9",
                "a_sym": "ac331db2-7951-4261-8a5c-6056e6b68ca9"
            }
        }
    ],
    "Path 2": [
        {
            "treeNode": {
                "nodeId": "3",
                "uid": "33559c94-f0cd-4cf0-a1e6-e313f2d8e3b4"
            },
            "predicate": "(Eq false (Slt (ReadLSB w32 0 b_sym) (ReadLSB w32 0 a_sym)))",
            "nodeTrueQuery": [
                "(Sle (ReadLSB w32 0 b_sym) 20)",
                "(Sle 0 (ReadLSB w32 0 c_prob_sym))",
                "(Sle (ReadLSB w32 0 c_prob_sym) 800)",
                "(Sle 0 (ReadLSB w32 0 d_prob_sym))",
                "(Sle (ReadLSB w32 0 d_prob_sym) 650)",
                "(Eq false (Slt (ReadLSB w32 0 b_sym) (ReadLSB w32 0 a_sym)))",
                "(Slt (ReadLSB w32 0 d_prob_sym) (ReadLSB w32 0 c_prob_sym))"
            ],
            "nodeFalseQuery": [
                "(Sle (ReadLSB w32 0 b_sym) 20)",
                "(Sle 0 (ReadLSB w32 0 c_prob_sym))",
                "(Sle (ReadLSB w32 0 c_prob_sym) 800)",
                "(Sle 0 (ReadLSB w32 0 d_prob_sym))",
                "(Sle (ReadLSB w32 0 d_prob_sym) 650)",
                "(Eq false (Slt (ReadLSB w32 0 b_sym) (ReadLSB w32 0 a_sym)))",
                "(Eq false (Slt (ReadLSB w32 0 d_prob_sym) (ReadLSB w32 0 c_prob_sym)))"
            ],
            "variables": [
                "b_sym",
                "a_sym"
            ],
            "IMap": {
                "d_prob_sym": "4193f29c-7352-47cb-9543-3d23c890dca9",
                "c_prob_sym": "4193f29c-7352-47cb-9543-3d23c890dca9",
                "b_sym": "a265962c-6288-44bc-aeb7-c986c42200ae",
                "a_sym": "a265962c-6288-44bc-aeb7-c986c42200ae"
            }
        },
        {
            "treeNode": {
                "nodeId": "5",
                "uid": "52bc4696-8944-474c-b6ea-b9eb602cd7df"
            },
            "predicate": "(Eq false (Slt (ReadLSB w32 0 d_prob_sym) (ReadLSB w32 0 c_prob_sym)))",
            "nodeTrueQuery": [],
            "nodeFalseQuery": [],
            "variables": [
                "d_prob_sym",
                "c_prob_sym"
            ],
            "IMap": {
                "d_prob_sym": "4193f29c-7352-47cb-9543-3d23c890dca9",
                "c_prob_sym": "4193f29c-7352-47cb-9543-3d23c890dca9",
                "b_sym": "a265962c-6288-44bc-aeb7-c986c42200ae",
                "a_sym": "a265962c-6288-44bc-aeb7-c986c42200ae"
            }
        }
    ],
    "Path 3": [
        {
            "treeNode": {
                "nodeId": "3",
                "uid": "33559c94-f0cd-4cf0-a1e6-e313f2d8e3b4"
            },
            "predicate": "(Eq false (Slt (ReadLSB w32 0 b_sym) (ReadLSB w32 0 a_sym)))",
            "nodeTrueQuery": [
                "(Sle (ReadLSB w32 0 b_sym) 20)",
                "(Sle 0 (ReadLSB w32 0 c_prob_sym))",
                "(Sle (ReadLSB w32 0 c_prob_sym) 800)",
                "(Sle 0 (ReadLSB w32 0 d_prob_sym))",
                "(Sle (ReadLSB w32 0 d_prob_sym) 650)",
                "(Eq false (Slt (ReadLSB w32 0 b_sym) (ReadLSB w32 0 a_sym)))",
                "(Slt (ReadLSB w32 0 d_prob_sym) (ReadLSB w32 0 c_prob_sym))"
            ],
            "nodeFalseQuery": [
                "(Sle (ReadLSB w32 0 b_sym) 20)",
                "(Sle 0 (ReadLSB w32 0 c_prob_sym))",
                "(Sle (ReadLSB w32 0 c_prob_sym) 800)",
                "(Sle 0 (ReadLSB w32 0 d_prob_sym))",
                "(Sle (ReadLSB w32 0 d_prob_sym) 650)",
                "(Eq false (Slt (ReadLSB w32 0 b_sym) (ReadLSB w32 0 a_sym)))",
                "(Eq false (Slt (ReadLSB w32 0 d_prob_sym) (ReadLSB w32 0 c_prob_sym)))"
            ],
            "variables": [
                "b_sym",
                "a_sym"
            ],
            "IMap": {
                "a_sym": "3143ae6a-2590-42b2-afee-d094a8c048d4",
                "b_sym": "3143ae6a-2590-42b2-afee-d094a8c048d4",
                "d_prob_sym": "9a84b186-b7b6-491b-a44c-b55770344d0e",
                "c_prob_sym": "9a84b186-b7b6-491b-a44c-b55770344d0e"
            }
        },
        {
            "treeNode": {
                "nodeId": "4",
                "uid": "77e9dfd9-a334-45e4-a4e5-bed5edef3e54"
            },
            "predicate": "(Slt (ReadLSB w32 0 d_prob_sym) (ReadLSB w32 0 c_prob_sym))",
            "nodeTrueQuery": [
                "(Sle (ReadLSB w32 0 b_sym) 20)",
                "(Sle 0 (ReadLSB w32 0 c_prob_sym))",
                "(Sle (ReadLSB w32 0 c_prob_sym) 800)",
                "(Sle 0 (ReadLSB w32 0 d_prob_sym))",
                "(Sle (ReadLSB w32 0 d_prob_sym) 650)",
                "(Eq false (Slt (ReadLSB w32 0 b_sym) (ReadLSB w32 0 a_sym)))",
                "(Slt (ReadLSB w32 0 d_prob_sym) (ReadLSB w32 0 c_prob_sym))",
                "(Sle 0 (ReadLSB w32 0 a_sym))"
            ],
            "nodeFalseQuery": [
                "(Sle (ReadLSB w32 0 b_sym) 20)",
                "(Sle 0 (ReadLSB w32 0 c_prob_sym))",
                "(Sle (ReadLSB w32 0 c_prob_sym) 800)",
                "(Sle 0 (ReadLSB w32 0 d_prob_sym))",
                "(Sle (ReadLSB w32 0 d_prob_sym) 650)",
                "(Eq false (Slt (ReadLSB w32 0 b_sym) (ReadLSB w32 0 a_sym)))",
                "(Slt (ReadLSB w32 0 d_prob_sym) (ReadLSB w32 0 c_prob_sym))",
                "(Eq false (Sle 0 (ReadLSB w32 0 a_sym)))"
            ],
            "variables": [
                "d_prob_sym",
                "c_prob_sym"
            ],
            "IMap": {
                "a_sym": "3143ae6a-2590-42b2-afee-d094a8c048d4",
                "b_sym": "3143ae6a-2590-42b2-afee-d094a8c048d4",
                "d_prob_sym": "9a84b186-b7b6-491b-a44c-b55770344d0e",
                "c_prob_sym": "9a84b186-b7b6-491b-a44c-b55770344d0e"
            }
        },
        {
            "treeNode": {
                "nodeId": "6",
                "uid": "583a6040-1765-4e3e-a438-074c5683624f"
            },
            "predicate": "(And (Sle 0 (ReadLSB w32 0 a_sym)) (Sle 0 (ReadLSB w32 0 b_sym)))",
            "nodeTrueQuery": [],
            "nodeFalseQuery": [],
            "variables": [
                "a_sym",
                "b_sym"
            ],
            "IMap": {
                "a_sym": "3143ae6a-2590-42b2-afee-d094a8c048d4",
                "b_sym": "3143ae6a-2590-42b2-afee-d094a8c048d4",
                "d_prob_sym": "9a84b186-b7b6-491b-a44c-b55770344d0e",
                "c_prob_sym": "9a84b186-b7b6-491b-a44c-b55770344d0e"
            }
        }
    ],
    "Path 4": [
        {
            "treeNode": {
                "nodeId": "3",
                "uid": "33559c94-f0cd-4cf0-a1e6-e313f2d8e3b4"
            },
            "predicate": "(Eq false (Slt (ReadLSB w32 0 b_sym) (ReadLSB w32 0 a_sym)))",
            "nodeTrueQuery": [
                "(Sle (ReadLSB w32 0 b_sym) 20)",
                "(Sle 0 (ReadLSB w32 0 c_prob_sym))",
                "(Sle (ReadLSB w32 0 c_prob_sym) 800)",
                "(Sle 0 (ReadLSB w32 0 d_prob_sym))",
                "(Sle (ReadLSB w32 0 d_prob_sym) 650)",
                "(Eq false (Slt (ReadLSB w32 0 b_sym) (ReadLSB w32 0 a_sym)))",
                "(Slt (ReadLSB w32 0 d_prob_sym) (ReadLSB w32 0 c_prob_sym))"
            ],
            "nodeFalseQuery": [
                "(Sle (ReadLSB w32 0 b_sym) 20)",
                "(Sle 0 (ReadLSB w32 0 c_prob_sym))",
                "(Sle (ReadLSB w32 0 c_prob_sym) 800)",
                "(Sle 0 (ReadLSB w32 0 d_prob_sym))",
                "(Sle (ReadLSB w32 0 d_prob_sym) 650)",
                "(Eq false (Slt (ReadLSB w32 0 b_sym) (ReadLSB w32 0 a_sym)))",
                "(Eq false (Slt (ReadLSB w32 0 d_prob_sym) (ReadLSB w32 0 c_prob_sym)))"
            ],
            "variables": [
                "b_sym",
                "a_sym"
            ],
            "IMap": {
                "a_sym": "d4920fcd-0f09-4be2-967e-8e2379ad6ab7",
                "b_sym": "d4920fcd-0f09-4be2-967e-8e2379ad6ab7",
                "d_prob_sym": "8d902834-88f8-4158-b142-9002bb738ff4",
                "c_prob_sym": "8d902834-88f8-4158-b142-9002bb738ff4"
            }
        },
        {
            "treeNode": {
                "nodeId": "4",
                "uid": "77e9dfd9-a334-45e4-a4e5-bed5edef3e54"
            },
            "predicate": "(Slt (ReadLSB w32 0 d_prob_sym) (ReadLSB w32 0 c_prob_sym))",
            "nodeTrueQuery": [
                "(Sle (ReadLSB w32 0 b_sym) 20)",
                "(Sle 0 (ReadLSB w32 0 c_prob_sym))",
                "(Sle (ReadLSB w32 0 c_prob_sym) 800)",
                "(Sle 0 (ReadLSB w32 0 d_prob_sym))",
                "(Sle (ReadLSB w32 0 d_prob_sym) 650)",
                "(Eq false (Slt (ReadLSB w32 0 b_sym) (ReadLSB w32 0 a_sym)))",
                "(Slt (ReadLSB w32 0 d_prob_sym) (ReadLSB w32 0 c_prob_sym))",
                "(Sle 0 (ReadLSB w32 0 a_sym))"
            ],
            "nodeFalseQuery": [
                "(Sle (ReadLSB w32 0 b_sym) 20)",
                "(Sle 0 (ReadLSB w32 0 c_prob_sym))",
                "(Sle (ReadLSB w32 0 c_prob_sym) 800)",
                "(Sle 0 (ReadLSB w32 0 d_prob_sym))",
                "(Sle (ReadLSB w32 0 d_prob_sym) 650)",
                "(Eq false (Slt (ReadLSB w32 0 b_sym) (ReadLSB w32 0 a_sym)))",
                "(Slt (ReadLSB w32 0 d_prob_sym) (ReadLSB w32 0 c_prob_sym))",
                "(Eq false (Sle 0 (ReadLSB w32 0 a_sym)))"
            ],
            "variables": [
                "d_prob_sym",
                "c_prob_sym"
            ],
            "IMap": {
                "a_sym": "d4920fcd-0f09-4be2-967e-8e2379ad6ab7",
                "b_sym": "d4920fcd-0f09-4be2-967e-8e2379ad6ab7",
                "d_prob_sym": "8d902834-88f8-4158-b142-9002bb738ff4",
                "c_prob_sym": "8d902834-88f8-4158-b142-9002bb738ff4"
            }
        },
        {
            "treeNode": {
                "nodeId": "7",
                "uid": "1e932542-1dbb-41dc-9d5a-86daa1edee4f"
            },
            "predicate": "(Eq false (And (Sle 0 (ReadLSB w32 0 a_sym)) (Sle 0 (ReadLSB w32 0 b_sym))))",
            "nodeTrueQuery": [
                "(Sle (ReadLSB w32 0 b_sym) 20)",
                "(Sle 0 (ReadLSB w32 0 c_prob_sym))",
                "(Sle (ReadLSB w32 0 c_prob_sym) 800)",
                "(Sle 0 (ReadLSB w32 0 d_prob_sym))",
                "(Sle (ReadLSB w32 0 d_prob_sym) 650)",
                "(Eq false (Slt (ReadLSB w32 0 b_sym) (ReadLSB w32 0 a_sym)))",
                "(Slt (ReadLSB w32 0 d_prob_sym) (ReadLSB w32 0 c_prob_sym))",
                "(Eq false (Sle 0 (ReadLSB w32 0 a_sym)))",
                "(Slt 0 (Mul w32 3 (ReadLSB w32 0 a_sym)))"
            ],
            "nodeFalseQuery": [
                "(Sle (ReadLSB w32 0 b_sym) 20)",
                "(Sle 0 (ReadLSB w32 0 c_prob_sym))",
                "(Sle (ReadLSB w32 0 c_prob_sym) 800)",
                "(Sle 0 (ReadLSB w32 0 d_prob_sym))",
                "(Sle (ReadLSB w32 0 d_prob_sym) 650)",
                "(Eq false (Slt (ReadLSB w32 0 b_sym) (ReadLSB w32 0 a_sym)))",
                "(Slt (ReadLSB w32 0 d_prob_sym) (ReadLSB w32 0 c_prob_sym))",
                "(Eq false (Sle 0 (ReadLSB w32 0 a_sym)))",
                "(Eq false (Slt 0 (Mul w32 3 (ReadLSB w32 0 a_sym))))"
            ],
            "variables": [
                "a_sym",
                "b_sym"
            ],
            "IMap": {
                "a_sym": "d4920fcd-0f09-4be2-967e-8e2379ad6ab7",
                "b_sym": "d4920fcd-0f09-4be2-967e-8e2379ad6ab7",
                "d_prob_sym": "8d902834-88f8-4158-b142-9002bb738ff4",
                "c_prob_sym": "8d902834-88f8-4158-b142-9002bb738ff4"
            }
        },
        {
            "treeNode": {
                "nodeId": "8",
                "uid": "5222039a-1d10-46ec-a738-afbbc1584620"
            },
            "predicate": "(Slt 0 (Mul w32 3 (ReadLSB w32 0 a_sym)))",
            "nodeTrueQuery": [],
            "nodeFalseQuery": [],
            "variables": [
                "a_sym"
            ],
            "IMap": {
                "a_sym": "d4920fcd-0f09-4be2-967e-8e2379ad6ab7",
                "b_sym": "d4920fcd-0f09-4be2-967e-8e2379ad6ab7",
                "d_prob_sym": "8d902834-88f8-4158-b142-9002bb738ff4",
                "c_prob_sym": "8d902834-88f8-4158-b142-9002bb738ff4"
            }
        }
    ],
    "Path 5": [
        {
            "treeNode": {
                "nodeId": "3",
                "uid": "33559c94-f0cd-4cf0-a1e6-e313f2d8e3b4"
            },
            "predicate": "(Eq false (Slt (ReadLSB w32 0 b_sym) (ReadLSB w32 0 a_sym)))",
            "nodeTrueQuery": [
                "(Sle (ReadLSB w32 0 b_sym) 20)",
                "(Sle 0 (ReadLSB w32 0 c_prob_sym))",
                "(Sle (ReadLSB w32 0 c_prob_sym) 800)",
                "(Sle 0 (ReadLSB w32 0 d_prob_sym))",
                "(Sle (ReadLSB w32 0 d_prob_sym) 650)",
                "(Eq false (Slt (ReadLSB w32 0 b_sym) (ReadLSB w32 0 a_sym)))",
                "(Slt (ReadLSB w32 0 d_prob_sym) (ReadLSB w32 0 c_prob_sym))"
            ],
            "nodeFalseQuery": [
                "(Sle (ReadLSB w32 0 b_sym) 20)",
                "(Sle 0 (ReadLSB w32 0 c_prob_sym))",
                "(Sle (ReadLSB w32 0 c_prob_sym) 800)",
                "(Sle 0 (ReadLSB w32 0 d_prob_sym))",
                "(Sle (ReadLSB w32 0 d_prob_sym) 650)",
                "(Eq false (Slt (ReadLSB w32 0 b_sym) (ReadLSB w32 0 a_sym)))",
                "(Eq false (Slt (ReadLSB w32 0 d_prob_sym) (ReadLSB w32 0 c_prob_sym)))"
            ],
            "variables": [
                "b_sym",
                "a_sym"
            ],
            "IMap": {
                "a_sym": "401660ba-5477-4d7e-8741-036ca4dc3c52",
                "b_sym": "401660ba-5477-4d7e-8741-036ca4dc3c52",
                "d_prob_sym": "6ac0040b-3ebb-4b24-a02f-04578b12f889",
                "c_prob_sym": "6ac0040b-3ebb-4b24-a02f-04578b12f889"
            }
        },
        {
            "treeNode": {
                "nodeId": "4",
                "uid": "77e9dfd9-a334-45e4-a4e5-bed5edef3e54"
            },
            "predicate": "(Slt (ReadLSB w32 0 d_prob_sym) (ReadLSB w32 0 c_prob_sym))",
            "nodeTrueQuery": [
                "(Sle (ReadLSB w32 0 b_sym) 20)",
                "(Sle 0 (ReadLSB w32 0 c_prob_sym))",
                "(Sle (ReadLSB w32 0 c_prob_sym) 800)",
                "(Sle 0 (ReadLSB w32 0 d_prob_sym))",
                "(Sle (ReadLSB w32 0 d_prob_sym) 650)",
                "(Eq false (Slt (ReadLSB w32 0 b_sym) (ReadLSB w32 0 a_sym)))",
                "(Slt (ReadLSB w32 0 d_prob_sym) (ReadLSB w32 0 c_prob_sym))",
                "(Sle 0 (ReadLSB w32 0 a_sym))"
            ],
            "nodeFalseQuery": [
                "(Sle (ReadLSB w32 0 b_sym) 20)",
                "(Sle 0 (ReadLSB w32 0 c_prob_sym))",
                "(Sle (ReadLSB w32 0 c_prob_sym) 800)",
                "(Sle 0 (ReadLSB w32 0 d_prob_sym))",
                "(Sle (ReadLSB w32 0 d_prob_sym) 650)",
                "(Eq false (Slt (ReadLSB w32 0 b_sym) (ReadLSB w32 0 a_sym)))",
                "(Slt (ReadLSB w32 0 d_prob_sym) (ReadLSB w32 0 c_prob_sym))",
                "(Eq false (Sle 0 (ReadLSB w32 0 a_sym)))"
            ],
            "variables": [
                "d_prob_sym",
                "c_prob_sym"
            ],
            "IMap": {
                "a_sym": "401660ba-5477-4d7e-8741-036ca4dc3c52",
                "b_sym": "401660ba-5477-4d7e-8741-036ca4dc3c52",
                "d_prob_sym": "6ac0040b-3ebb-4b24-a02f-04578b12f889",
                "c_prob_sym": "6ac0040b-3ebb-4b24-a02f-04578b12f889"
            }
        },
        {
            "treeNode": {
                "nodeId": "7",
                "uid": "1e932542-1dbb-41dc-9d5a-86daa1edee4f"
            },
            "predicate": "(Eq false (And (Sle 0 (ReadLSB w32 0 a_sym)) (Sle 0 (ReadLSB w32 0 b_sym))))",
            "nodeTrueQuery": [
                "(Sle (ReadLSB w32 0 b_sym) 20)",
                "(Sle 0 (ReadLSB w32 0 c_prob_sym))",
                "(Sle (ReadLSB w32 0 c_prob_sym) 800)",
                "(Sle 0 (ReadLSB w32 0 d_prob_sym))",
                "(Sle (ReadLSB w32 0 d_prob_sym) 650)",
                "(Eq false (Slt (ReadLSB w32 0 b_sym) (ReadLSB w32 0 a_sym)))",
                "(Slt (ReadLSB w32 0 d_prob_sym) (ReadLSB w32 0 c_prob_sym))",
                "(Eq false (Sle 0 (ReadLSB w32 0 a_sym)))",
                "(Slt 0 (Mul w32 3 (ReadLSB w32 0 a_sym)))"
            ],
            "nodeFalseQuery": [
                "(Sle (ReadLSB w32 0 b_sym) 20)",
                "(Sle 0 (ReadLSB w32 0 c_prob_sym))",
                "(Sle (ReadLSB w32 0 c_prob_sym) 800)",
                "(Sle 0 (ReadLSB w32 0 d_prob_sym))",
                "(Sle (ReadLSB w32 0 d_prob_sym) 650)",
                "(Eq false (Slt (ReadLSB w32 0 b_sym) (ReadLSB w32 0 a_sym)))",
                "(Slt (ReadLSB w32 0 d_prob_sym) (ReadLSB w32 0 c_prob_sym))",
                "(Eq false (Sle 0 (ReadLSB w32 0 a_sym)))",
                "(Eq false (Slt 0 (Mul w32 3 (ReadLSB w32 0 a_sym))))"
            ],
            "variables": [
                "a_sym",
                "b_sym"
            ],
            "IMap": {
                "a_sym": "401660ba-5477-4d7e-8741-036ca4dc3c52",
                "b_sym": "401660ba-5477-4d7e-8741-036ca4dc3c52",
                "d_prob_sym": "6ac0040b-3ebb-4b24-a02f-04578b12f889",
                "c_prob_sym": "6ac0040b-3ebb-4b24-a02f-04578b12f889"
            }
        },
        {
            "treeNode": {
                "nodeId": "9",
                "uid": "5b187bdd-b73b-47bf-8ddd-3a98fee30d4c"
            },
            "predicate": "(Eq false (Slt 0 (Mul w32 3 (ReadLSB w32 0 a_sym))))",
            "nodeTrueQuery": [],
            "nodeFalseQuery": [],
            "variables": [
                "a_sym"
            ],
            "IMap": {
                "a_sym": "401660ba-5477-4d7e-8741-036ca4dc3c52",
                "b_sym": "401660ba-5477-4d7e-8741-036ca4dc3c52",
                "d_prob_sym": "6ac0040b-3ebb-4b24-a02f-04578b12f889",
                "c_prob_sym": "6ac0040b-3ebb-4b24-a02f-04578b12f889"
            }
        }
    ]
}